splitpatch/__init__.py
splitpatch/__main__.py
splitpatch/cli.py
splitpatch/merge.py
splitpatch/patch.py
splitpatch/profiling.py
splitpatch/tree.py
splitpatch-1.0.6.dist-info/licenses/LICENSE
splitpatch-1.0.6.dist-info/METADATA
splitpatch-1.0.6.dist-info/WHEEL
splitpatch-1.0.6.dist-info/entry_points.txt
splitpatch-1.0.6.dist-info/top_level.txt
splitpatch-1.0.6.dist-info/RECORD
