Metadata-Version: 2.4
Name: splitpatch
Version: 1.0.6
Summary: An intelligent tool for splitting large patch files into smaller file-based patches
Author-email: Chao Liu <chaoliu719@gmail.com>
License-Expression: MIT
Project-URL: Homepage, https://github.com/chaoliu719/splitpatch
Project-URL: Issues, https://github.com/chaoliu719/splitpatch/issues
Classifier: Programming Language :: Python :: 3
Classifier: Operating System :: OS Independent
Requires-Python: >=3.8
License-File: LICENSE
Dynamic: license-file
